{
  "updated_at": "2025-12-29T03:29:55.141341Z",
  "location": {
    "name": "Lommedalen",
    "latitude": 59.95,
    "longitude": 10.466667,
    "yr_location_id": "1-72662"
  },
  "sun_times": {
    "sunrise": "2025-12-29T08:17:34+00:00",
    "sunset": "2025-12-29T14:22:56+00:00",
    "solar_noon": "2025-12-29T11:20:15+00:00",
    "day_length": 21922,
    "civil_twilight_begin": "2025-12-29T07:23:51+00:00",
    "civil_twilight_end": "2025-12-29T15:16:38+00:00",
    "nautical_twilight_begin": "2025-12-29T06:27:26+00:00",
    "nautical_twilight_end": "2025-12-29T16:13:04+00:00",
    "astronomical_twilight_begin": "2025-12-29T05:36:09+00:00",
    "astronomical_twilight_end": "2025-12-29T17:04:21+00:00"
  },
  "dark_hours": {
    "start_hour": 17,
    "end_hour": 5,
    "spans_midnight": true
  },
  "cron_schedules": [
    "*/15 17-23 * * *",
    "*/15 0-5 * * *"
  ]
}