{
  "updated_at": "2026-03-19T04:12:32.372544Z",
  "location": {
    "name": "Lommedalen",
    "latitude": 59.95,
    "longitude": 10.466667,
    "yr_location_id": "1-72662"
  },
  "sun_times": {
    "sunrise": "2026-03-19T05:20:11+00:00",
    "sunset": "2026-03-19T17:31:35+00:00",
    "solar_noon": "2026-03-19T11:25:53+00:00",
    "day_length": 43884,
    "civil_twilight_begin": "2026-03-19T04:40:51+00:00",
    "civil_twilight_end": "2026-03-19T18:10:55+00:00",
    "nautical_twilight_begin": "2026-03-19T03:51:09+00:00",
    "nautical_twilight_end": "2026-03-19T19:00:37+00:00",
    "astronomical_twilight_begin": "2026-03-19T02:57:23+00:00",
    "astronomical_twilight_end": "2026-03-19T19:54:23+00:00"
  },
  "dark_hours": {
    "start_hour": 20,
    "end_hour": 2,
    "spans_midnight": true
  },
  "cron_schedules": [
    "*/15 20-23 * * *",
    "*/15 0-2 * * *"
  ]
}